asyncclick_option_group/__init__.py
asyncclick_option_group/_core.py
asyncclick_option_group/_decorators.py
asyncclick_option_group/_helpers.py
asyncclick_option_group/_version.py
asyncclick_option_group/py.typed
asyncclick_option_group-0.5.6.1.dist-info/METADATA
asyncclick_option_group-0.5.6.1.dist-info/WHEEL
asyncclick_option_group-0.5.6.1.dist-info/licenses/LICENSE
asyncclick_option_group-0.5.6.1.dist-info/RECORD
