Metadata-Version: 2.1
Name: asyncclick-option-group
Version: 0.5.6.1
Summary: Option groups missing in AsyncClick
Project-URL: Homepage, https://github.com/smurfix/asyncclick-option-group
Project-URL: Code, https://github.com/smurfix/asyncclick-option-group
Project-URL: Documentation, https://click-option-group.readthedocs.io
Project-URL: Issues, https://github.com/smurfix/asyncclick-option-group/issues
Author-email: Matthias Urlichs <matthias@urlichs.de>, Eugene Prilepin <esp.home@gmail.com>
License-Expression: BSD-3-Clause
License-File: LICENSE
Classifier: Development Status :: 4 - Beta
Classifier: Environment :: Console
Classifier: Intended Audience :: Developers
Classifier: License :: OSI Approved :: BSD License
Classifier: Operating System :: OS Independent
Classifier: Programming Language :: Python
Classifier: Programming Language :: Python :: 3
Classifier: Programming Language :: Python :: 3 :: Only
Classifier: Programming Language :: Python :: 3.6
Classifier: Programming Language :: Python :: 3.7
Classifier: Programming Language :: Python :: 3.8
Classifier: Programming Language :: Python :: 3.9
Classifier: Programming Language :: Python :: 3.10
Classifier: Programming Language :: Python :: 3.11
Classifier: Topic :: Software Development :: Libraries
Requires-Python: >=3.6
Requires-Dist: asyncclick>=7.0
Provides-Extra: dev
Requires-Dist: click-option-group[test]; extra == 'dev'
Requires-Dist: pre-commit; extra == 'dev'
Provides-Extra: docs
Requires-Dist: m2r2; extra == 'docs'
Requires-Dist: pallets-sphinx-themes; extra == 'docs'
Requires-Dist: sphinx; extra == 'docs'
Provides-Extra: test
Requires-Dist: pytest; extra == 'test'
Provides-Extra: test-cov
Requires-Dist: click-option-group[test]; extra == 'test-cov'
Requires-Dist: pytest-cov; extra == 'test-cov'
